LICENSE
README.md
setup.py
bin/yedb
yedb/__init__.py
yedb/cli.py
yedb/common.py
yedb/server.py
yedb.egg-info/PKG-INFO
yedb.egg-info/SOURCES.txt
yedb.egg-info/dependency_links.txt
yedb.egg-info/requires.txt
yedb.egg-info/top_level.txt