Metadata-Version: 2.1
Name: yedb
Version: 0.2.23
Summary: Rugged embedded and client/server key/value database
Home-page: https://github.com/alttch/yedb
Author: Altertech
Author-email: pr@altertech.com
License: Apache License 2.0
Platform: UNKNOWN
Classifier: Programming Language :: Python :: 3
Classifier: License :: OSI Approved :: Apache Software License
Classifier: Topic :: Database
Classifier: Topic :: Database :: Database Engines/Servers
Provides-Extra: cli
License-File: LICENSE
